fretpkg/__init__.py
fretpkg/fretfinder.py
frets4ever-0.0.1.dist-info/LICENSE
frets4ever-0.0.1.dist-info/METADATA
frets4ever-0.0.1.dist-info/WHEEL
frets4ever-0.0.1.dist-info/top_level.txt
frets4ever-0.0.1.dist-info/RECORD
